odoo8_addon_crm_sale_marketing-8.0.2.0.0.99.dev4-nspkg.pth
odoo_addons/crm_sale_marketing/README.rst
odoo_addons/crm_sale_marketing/__init__.py
odoo_addons/crm_sale_marketing/__openerp__.py
odoo_addons/crm_sale_marketing/i18n/crm_sale_marketing.pot
odoo_addons/crm_sale_marketing/i18n/de.po
odoo_addons/crm_sale_marketing/i18n/es.po
odoo_addons/crm_sale_marketing/i18n/sl.po
odoo_addons/crm_sale_marketing/static/description/icon.png
odoo_addons/crm_sale_marketing/tests/__init__.py
odoo_addons/crm_sale_marketing/tests/test_crm_sale_marketing.py
odoo_addons/crm_sale_marketing/wizards/__init__.py
odoo_addons/crm_sale_marketing/wizards/crm_make_sale.py
odoo8_addon_crm_sale_marketing-8.0.2.0.0.99.dev4.dist-info/METADATA
odoo8_addon_crm_sale_marketing-8.0.2.0.0.99.dev4.dist-info/WHEEL
odoo8_addon_crm_sale_marketing-8.0.2.0.0.99.dev4.dist-info/namespace_packages.txt
odoo8_addon_crm_sale_marketing-8.0.2.0.0.99.dev4.dist-info/top_level.txt
odoo8_addon_crm_sale_marketing-8.0.2.0.0.99.dev4.dist-info/RECORD
