Metadata-Version: 2.1
Name: odoo8-addon-crm-sale-marketing
Version: 8.0.2.0.0.99.dev4
Summary: Marketing Details of Sales
Home-page: https://github.com/OCA/crm
Author: Eficent, Serpent Consulting Services Pvt. Ltd.,Odoo Community Association (OCA)
Author-email: support@odoo-community.org
License: AGPL-3
Platform: UNKNOWN
Classifier: Programming Language :: Python
Classifier: Framework :: Odoo
Classifier: License :: OSI Approved :: GNU Affero General Public License v3
Requires-Python: ~=2.7
Requires-Dist: odoo (<9.0a,>=8.0a)
